pyzswagcl/LICENSE.txt
pyzswagcl/__init__.py
pyzswagcl/libhttpcl.a
pyzswagcl/libz.so
pyzswagcl/libz.so.1
pyzswagcl/libz.so.1.3.1
pyzswagcl/libzswagcl.so
pyzswagcl/pyzswagcl.cpython-313-aarch64-linux-gnu.so
pyzswagcl.egg-info/PKG-INFO
pyzswagcl.egg-info/SOURCES.txt
pyzswagcl.egg-info/dependency_links.txt
pyzswagcl.egg-info/top_level.txt
pyzswagcl.libs/libblkid-e4a77f31.so.1.1.0
pyzswagcl.libs/libffi-b23fa0bb.so.6.0.2
pyzswagcl.libs/libgcrypt-4af81264.so.20.2.5
pyzswagcl.libs/libgio-2-5d78a94c.0.so.0.5600.4
pyzswagcl.libs/libgmodule-2-49123bff.0.so.0.5600.4
pyzswagcl.libs/libgmp-6d1678ee.so.10.3.2
pyzswagcl.libs/libgnutls-5e16eaa5.so.30.28.2
pyzswagcl.libs/libgpg-error-6019f251.so.0.24.2
pyzswagcl.libs/libhogweed-2f02f501.so.4.5
pyzswagcl.libs/libidn2-1b2a13b7.so.0.3.6
pyzswagcl.libs/libmount-bbb803f3.so.1.1.0
pyzswagcl.libs/libnettle-f004dfb3.so.6.5
pyzswagcl.libs/libp11-kit-7399a377.so.0.3.0
pyzswagcl.libs/libpcre-1e9fb62f.so.1.2.10
pyzswagcl.libs/libpcre2-8-8701a61e.so.0.7.1
pyzswagcl.libs/libsecret-1-cd1a2c2f.so.0.0.0
pyzswagcl.libs/libselinux-5700a1fd.so.1
pyzswagcl.libs/libtasn1-87f4054b.so.6.5.5
pyzswagcl.libs/libunistring-be03fd41.so.2.1.0
pyzswagcl.libs/libuuid-8d96e403.so.1.3.0
pyzswagcl-1.11.1.dist-info/METADATA
pyzswagcl-1.11.1.dist-info/WHEEL
pyzswagcl-1.11.1.dist-info/top_level.txt
pyzswagcl-1.11.1.dist-info/RECORD
