Metadata-Version: 2.4
Name: pyzswagcl
Version: 1.11.1
Summary: Python bindings for the zswag client library.
Home-page: https://github.com/ndsev/zswag
Author: Navigation Data Standard e.V.
Author-email: 
Keywords: pyzswagcl
Requires-Python: >=3.9
Dynamic: author
Dynamic: home-page
Dynamic: keywords
Dynamic: requires-python
Dynamic: summary
